Metadata-Version: 1.1
Name: ECoXiPy
Version: 0.4.0
Summary: Easy Creation of XML in Python
Home-page: https://github.com/IvIePhisto/ECoXiPy
Author: Michael Pohl
Author-email: pohl-michael@gmx.biz
License: MIT License
Keywords: XML
Platform: UNKNOWN
Classifier: Development Status :: 5 - Production/Stable
Classifier: Intended Audience :: Developers
Classifier: License :: OSI Approved :: MIT License
Classifier: Natural Language :: English
Classifier: Operating System :: OS Independent
Classifier: Programming Language :: Python :: 2.7
Classifier: Programming Language :: Python :: 3.3
Classifier: Topic :: Software Development :: Libraries :: Python Modules
Classifier: Topic :: Text Processing :: Markup :: XML
